LICENCE
MANIFEST.in
README.md
setup.py
bigbrother/__init__.py
bigbrother/core.py
bigbrother/graphs.py
bigbrother/models.py
bigbrother/tasks.py
bigbrother/urls.py
bigbrother/views.py
bigbrother/warnings.py
bigbrother/management/__init__.py
bigbrother/management/commands/__init__.py
bigbrother/management/commands/update_bigbrother.py
bigbrother/migrations/0001_initial.py
bigbrother/migrations/0002_auto__chg_field_modulestat_value.py
bigbrother/migrations/__init__.py
bigbrother/static/css/dashboard.css
bigbrother/static/img/dashboard-bg.png
bigbrother/static/js/.DS_Store
bigbrother/static/js/jquery.flot.min.js
bigbrother/static/js/jquery.flot.time.min.js
bigbrother/templates/bigbrother/graph.html
bigbrother/templates/bigbrother/group.html
bigbrother/templates/bigbrother/index.html
django_bigbrother.egg-info/PKG-INFO
django_bigbrother.egg-info/SOURCES.txt
django_bigbrother.egg-info/dependency_links.txt
django_bigbrother.egg-info/not-zip-safe
django_bigbrother.egg-info/requires.txt
django_bigbrother.egg-info/top_level.txt