Metadata-Version: 1.1
Name: django-bigbrother
Version: 0.4.2
Summary: Modular Dashboard for Django Projects
Home-page: http://github.com/anderspetersson/django-bigbrother
Author: Anders Petersson
Author-email: me@anderspetersson.se
License: UNKNOWN
Keywords: django dashboard bigbrother monitoring
Platform: UNKNOWN
Classifier: Development Status :: 4 - Beta
Classifier: Intended Audience :: Developers
Classifier: Intended Audience :: System Administrators
Classifier: Topic :: Software Development :: Libraries :: Python Modules
Classifier: Topic :: System :: Monitoring
Classifier: Environment :: Web Environment
Classifier: Operating System :: Unix
Classifier: Programming Language :: Python
Classifier: Framework :: Django
